vedro_matrix/__init__.py
vedro_matrix/py.typed
vedro_matrix-1.0.0.dist-info/LICENSE
vedro_matrix-1.0.0.dist-info/METADATA
vedro_matrix-1.0.0.dist-info/WHEEL
vedro_matrix-1.0.0.dist-info/RECORD
